xiomedon/__init__.py
xiomedon/_version.py
xiomedon/openai_wrapper.py
xiomedon/__pycache__/openai.cpython-311.pyc
xiomedon/__pycache__/openai_wrapper.cpython-311.pyc
xiomedon-1.0.2.dist-info/LICENSE
xiomedon-1.0.2.dist-info/METADATA
xiomedon-1.0.2.dist-info/WHEEL
xiomedon-1.0.2.dist-info/top_level.txt
xiomedon-1.0.2.dist-info/RECORD
