Metadata-Version: 2.1
Name: xiomedon
Version: 1.0.2
Summary: Library to call Open AI gpt3.5t-turbo and collect reponses and check for Accuracy
Home-page: https://github.com/ashwinaravind/xiomedon
Author: Ashwin Aravind
Author-email: Ashwin Aravind <ashwinaravind@gmail.com>
Requires-Python: >=3.7
License-File: LICENSE
Requires-Dist: datasets
Requires-Dist: openai >1
Requires-Dist: pytest ==7.2.1
Requires-Dist: pytest-xdist ~=3.2.0
Requires-Dist: coverage ~=7.1.0
Requires-Dist: black ~=23.1.0
Requires-Dist: pytest-timeout ~=2.1.0
Requires-Dist: pytest-env ~=0.8.1
